Cosmos_Coin_Masternode_Setup-1.1.0.dist-info/DESCRIPTION.rst
Cosmos_Coin_Masternode_Setup-1.1.0.dist-info/METADATA
Cosmos_Coin_Masternode_Setup-1.1.0.dist-info/RECORD
Cosmos_Coin_Masternode_Setup-1.1.0.dist-info/WHEEL
Cosmos_Coin_Masternode_Setup-1.1.0.dist-info/entry_points.txt
Cosmos_Coin_Masternode_Setup-1.1.0.dist-info/metadata.json
Cosmos_Coin_Masternode_Setup-1.1.0.dist-info/top_level.txt
MasternodeSetup/command_line.py
MasternodeSetup/core.py
MasternodeSetup/daemon.py
MasternodeSetup/masternode.py
MasternodeSetup/vps.py
MasternodeSetup/conf/conf.template
MasternodeSetup/conf/config.ini
