Metadata-Version: 2.0
Name: Cosmos-Coin-Masternode-Setup
Version: 1.1.0
Summary: End to end script to setup a masternode
Home-page: https://github.com/mtmonte/MasternodeSetup
Author: mtmonte
Author-email: cosmos.mtmonte@gmail.com
License: MIT
Keywords: bitcoin cosmos coin crypto cryptocurrency masternode
Platform: UNKNOWN
Requires-Python: >=3.3.0
Requires-Dist: paramiko
